.test_nightly.conf.sample
.travis.conf.sample
README.rst
setup.py
travis_emulator/LICENSE
travis_emulator/__init__.py
travis_emulator/__main__.py
travis_emulator/cronow
travis_emulator/debug_set_env.sh
travis_emulator/make_travis_conf.py
travis_emulator/set_ssh_prot
travis_emulator/simulate_travis.sh
travis_emulator/template_travis.yml
travis_emulator/travis
travis_emulator/travis.man
travis_emulator/travis_tmp.sh
travis_emulator/travisrc
travis_emulator.egg-info/PKG-INFO
travis_emulator.egg-info/SOURCES.txt
travis_emulator.egg-info/dependency_links.txt
travis_emulator.egg-info/entry_points.txt
travis_emulator.egg-info/not-zip-safe
travis_emulator.egg-info/requires.txt
travis_emulator.egg-info/top_level.txt
travis_emulator/docs/MAINPAGE.rst
travis_emulator/docs/Makefile
travis_emulator/docs/conf.py
travis_emulator/docs/index.rst
travis_emulator/docs/logozero_180x46.png
travis_emulator/docs/readthedocs.yml
travis_emulator/docs/requirements.txt
travis_emulator/docs/rtd_automodule.rst
travis_emulator/docs/rtd_changelog.rst
travis_emulator/docs/rtd_credits.rst
travis_emulator/docs/rtd_description.rst
travis_emulator/docs/rtd_features.rst
travis_emulator/docs/rtd_getting_started.rst
travis_emulator/docs/rtd_usage.rst
travis_emulator/docs/rtd_usage_config.rst
travis_emulator/docs/_build/doctrees/MAINPAGE.doctree
travis_emulator/docs/_build/doctrees/environment.pickle
travis_emulator/docs/_build/doctrees/index.doctree
travis_emulator/docs/_build/html/.buildinfo
travis_emulator/docs/_build/html/.nojekyll
travis_emulator/docs/_build/html/MAINPAGE.html
travis_emulator/docs/_build/html/genindex.html
travis_emulator/docs/_build/html/index.html
travis_emulator/docs/_build/html/objects.inv
travis_emulator/docs/_build/html/search.html
travis_emulator/docs/_build/html/searchindex.js
travis_emulator/docs/_build/html/_sources/MAINPAGE.rst.txt
travis_emulator/docs/_build/html/_sources/index.rst.txt
travis_emulator/docs/_build/html/_static/_sphinx_javascript_frameworks_compat.js
travis_emulator/docs/_build/html/_static/basic.css
travis_emulator/docs/_build/html/_static/doctools.js
travis_emulator/docs/_build/html/_static/documentation_options.js
travis_emulator/docs/_build/html/_static/file.png
travis_emulator/docs/_build/html/_static/jquery-3.6.0.js
travis_emulator/egg-info/CHANGELOG.rst
travis_emulator/egg-info/DESCRIPTION.rst
travis_emulator/egg-info/TROUBLESHOOTING.rst
travis_emulator/egg-info/USAGE.rst
travis_emulator/egg-info/__manifest__.rst
travis_emulator/egg-info/features.csv
travis_emulator/egg-info/travis_phases.csv
travis_emulator/egg-info/usage_config.csv
