Metadata-Version: 1.2
Name: travis-emulator
Version: 2.0.11
Summary: Travis CI emulator for local develop environment
Home-page: https://zeroincombenze-tools.readthedocs.io
Author: Antonio Maria Vigliotti
Author-email: antoniomaria.vigliotti@gmail.com
License: GPL-3.0-or-later
Project-URL: Source, https://github.com/zeroincombenze/tools
Project-URL: Documentation, https://zeroincombenze-tools.readthedocs.io
Keywords: linux travis development
Platform: UNKNOWN
Classifier: Development Status :: 4 - Beta
Classifier: Operating System :: POSIX
Classifier: Programming Language :: Python :: 2.7
Classifier: Programming Language :: Python :: 3.7
Classifier: Programming Language :: Python :: 3.8
Classifier: Programming Language :: Python :: 3.9
Classifier: Programming Language :: Python :: 3.10
Classifier: Intended Audience :: Developers
Classifier: Topic :: Software Development
Classifier: Topic :: Software Development :: Build Tools
Classifier: Operating System :: OS Independent
